README.md
setup.py
modpybass/__init__.py
modpybass/bass.py
modpybass/pybass.py
modpybass/pybass_aac.py
modpybass/pybass_ac3.py
modpybass/pybass_adx.py
modpybass/pybass_aix.py
modpybass/pybass_alac.py
modpybass/pybass_ape.py
modpybass/pybass_mpc.py
modpybass/pybass_ofr.py
modpybass/pybass_sfx.py
modpybass/pybass_spx.py
modpybass/pybass_tta.py
modpybass/pybass_vst.py
modpybass/pybassasio.py
modpybass/pybassflac.py
modpybass/pybassmidi.py
modpybass/pybassmix.py
modpybass/pybasswasapi.py
modpybass/pybasswma.py
modpybass/pyogginfo.py
modpybass/pytags.py
modpybass/wx_bass_control.py
modpybass/wx_ctrl_phoenix.py
modpybass.egg-info/PKG-INFO
modpybass.egg-info/SOURCES.txt
modpybass.egg-info/dependency_links.txt
modpybass.egg-info/top_level.txt
modpybass/lib/x64/bass.dll
modpybass/lib/x64/bass_fx.dll
modpybass/lib/x64/bass_vst.dll
modpybass/lib/x64/bassmidi.dll
modpybass/lib/x64/bassmix.dll
modpybass/lib/x64/tags.dll
modpybass/lib/x86/bass.dll
modpybass/lib/x86/bass_fx.dll
modpybass/lib/x86/bass_vst.dll
modpybass/lib/x86/bassmidi.dll
modpybass/lib/x86/bassmix.dll
modpybass/lib/x86/tags.dll