Metadata-Version: 2.1
Name: modpybass
Version: 0.0.10
Summary: modified pybass
Home-page: https://github.com/peppy0510/modpybass
Author: Taehong Kim
Author-email: peppy0510@hotmail.com
License: Apache License 2.0
Keywords: bass pybass audio
Platform: UNKNOWN
Classifier: Development Status :: 3 - Alpha
Classifier: License :: OSI Approved :: Apache Software License
Classifier: Topic :: Multimedia :: Sound/Audio
